Metadata-Version: 2.1
Name: wrk-pyppeteer
Version: 1.0.2.1
Summary: Headless chrome/chromium automation library (unofficial port of puppeteer)
Home-page: https://github.com/pyppeteer/pyppeteer
License: MIT
Keywords: pyppeteer,puppeteer,chrome,chromium
Author: granitosaurus
Author-email: bernardas.alisauskas@pm.me
Requires-Python: >=3.7,<4.0
Classifier: Development Status :: 3 - Alpha
Classifier: Intended Audience :: Developers
Classifier: License :: OSI Approved :: MIT License
Classifier: Natural Language :: English
Classifier: Programming Language :: Python :: 3
Classifier: Programming Language :: Python :: 3.7
Classifier: Programming Language :: Python :: 3.8
Classifier: Programming Language :: Python :: 3.9
Classifier: Programming Language :: Python :: 3.10
Classifier: Programming Language :: Python :: 3.11
Requires-Dist: appdirs (>=1.4.3,<2.0.0)
Requires-Dist: certifi (>=2021)
Requires-Dist: importlib-metadata (>=1.4)
Requires-Dist: pyee (>=8.1.0,<9.0.0)
Requires-Dist: tqdm (>=4.42.1,<5.0.0)
Requires-Dist: urllib3 (>=1.25.8,<2.0.0)
Requires-Dist: websockets (>=10.0,<11.0)
Project-URL: Bug Tracker, https://github.com/pyppeteer/pyppeteer/issues
Project-URL: Repository, https://github.com/pyppeteer/pyppeteer
